odoo/addons/sale_double_validation/README.rst
odoo/addons/sale_double_validation/__init__.py
odoo/addons/sale_double_validation/__manifest__.py
odoo/addons/sale_double_validation/i18n/de.po
odoo/addons/sale_double_validation/i18n/sale_double_validation.pot
odoo/addons/sale_double_validation/i18n/zh_CN.po
odoo/addons/sale_double_validation/models/__init__.py
odoo/addons/sale_double_validation/models/company.py
odoo/addons/sale_double_validation/models/sale.py
odoo/addons/sale_double_validation/readme/CONFIGURE.rst
odoo/addons/sale_double_validation/readme/CONTRIBUTORS.rst
odoo/addons/sale_double_validation/readme/DESCRIPTION.rst
odoo/addons/sale_double_validation/readme/USAGE.rst
odoo/addons/sale_double_validation/static/description/icon.png
odoo/addons/sale_double_validation/static/description/index.html
odoo/addons/sale_double_validation/tests/__init__.py
odoo/addons/sale_double_validation/tests/test_double_validation.py
odoo/addons/sale_double_validation/views/company.xml
odoo/addons/sale_double_validation/views/sale.xml
odoo12_addon_sale_double_validation-12.0.1.0.1.dist-info/METADATA
odoo12_addon_sale_double_validation-12.0.1.0.1.dist-info/WHEEL
odoo12_addon_sale_double_validation-12.0.1.0.1.dist-info/top_level.txt
odoo12_addon_sale_double_validation-12.0.1.0.1.dist-info/RECORD
